dexml/__init__.py
dexml/fields.py
dexml/test.py
dexml3-2.0.0.dist-info/LICENSE.txt
dexml3-2.0.0.dist-info/METADATA
dexml3-2.0.0.dist-info/WHEEL
dexml3-2.0.0.dist-info/top_level.txt
dexml3-2.0.0.dist-info/RECORD
