Metadata-Version: 2.1
Name: dexml3
Version: 2.0.0
Summary: a dead-simple Object-XML mapper for Python
Author-email: Ryan Kelly <ryan@rfk.id.au>
Project-URL: Homepage, http://packages.python.org/dexml3
Classifier: Programming Language :: Python :: 3
Classifier: License :: OSI Approved :: MIT License
Classifier: Operating System :: OS Independent
Requires-Python: >=3.7
License-File: LICENSE.txt
